fake_useragent_kz/__init__.py
fake_useragent_kz/fake_useragent_kz.py
fake_useragent_kz-1.0.0.dist-info/METADATA
fake_useragent_kz-1.0.0.dist-info/WHEEL
fake_useragent_kz-1.0.0.dist-info/top_level.txt
fake_useragent_kz-1.0.0.dist-info/RECORD
