Metadata-Version: 2.1
Name: fake-useragent-kz
Version: 1.0.0
Summary: fake_useragent.
Home-page: https://github.com/me/myproject
Author: kz
Author-email: 767891749@qq.com
License: MIT
Platform: UNKNOWN
Classifier: License :: OSI Approved :: MIT License
Classifier: Programming Language :: Python
Classifier: Programming Language :: Python :: 3
Classifier: Programming Language :: Python :: 3.6
Classifier: Programming Language :: Python :: Implementation :: CPython
Classifier: Programming Language :: Python :: Implementation :: PyPy
Requires-Python: >=3.6.0
